potato_head-0.1.0.dist-info/METADATA
potato_head-0.1.0.dist-info/WHEEL
potato_head-0.1.0.dist-info/licenses/LICENSE
potato_head/openai/__init__.py
potato_head/openai/__init__.pyi
potato_head/anthropic/__init__.py
potato_head/anthropic/__init__.pyi
potato_head/version.py
potato_head/logging/__init__.py
potato_head/logging/__init__.pyi
potato_head/py.typed
potato_head/prompts/__init__.py
potato_head/prompts/__init__.pyi
potato_head/parts/__init__.py
potato_head/parts/__init__.pyi
potato_head/__init__.py
potato_head/test/__init__.py
potato_head/test/__init__.pyi
potato_head/__init__.pyi
potato_head/potato_head.cpython-310-x86_64-linux-gnu.so
potato_head-0.1.0.dist-info/RECORD
