Metadata-Version: 2.4
Name: potato-head
Version: 0.1.0
Classifier: Programming Language :: Rust
Classifier: Programming Language :: Python :: Implementation :: PyPy
License-File: LICENSE
Summary: 
Author-email: Thorrester <<support@demmlai.com>>
Requires-Python: >=3.10
Project-URL: Homepage, https://github.com/demml/potatohead
Project-URL: Source, https://github.com/demml/potatohead
